nao_logger/__init__.py
nao_logger/nao_logger.py
nao_logger-1.0.6.dist-info/METADATA
nao_logger-1.0.6.dist-info/WHEEL
nao_logger-1.0.6.dist-info/top_level.txt
nao_logger-1.0.6.dist-info/RECORD
